<?xml version="1.0" encoding="utf-16"?>
<Level width="2">
  <Camera x="0" y="-1" minWidth="25" maxWidth="35" />
  <Score highScore="958213" />
  <Birds>
    <Bird type="BirdRed" />
    <Bird type="BirdRed" />
    <Bird type="BirdRed" />
  </Birds>
  <Slingshot x="-12.0" y="-2.5" />
  <GameObjects>
    <Block type="Triangle" material="ice" x="1.50359" y="5.24032" rotation="89.70668" />
    <Block type="RectMedium" material="wood" x="1.50273" y="4.70672" rotation="359.6991" />
    <Block type="RectTiny" material="wood" x="0.77323" y="4.37133" rotation="89.72797" />
    <Block type="RectTiny" material="wood" x="1.07701" y="4.36988" rotation="89.59496" />
    <Block type="RectTiny" material="wood" x="1.92372" y="4.36589" rotation="89.66384" />
    <Block type="RectTiny" material="wood" x="2.23364" y="4.36389" rotation="89.63508" />
    <Block type="RectBig" material="ice" x="1.50061" y="4.03027" rotation="359.7233" />
    <Block type="RectSmall" material="wood" x="0.58474" y="3.80362" rotation="359.6877" />
    <Block type="RectSmall" material="wood" x="1.50229" y="3.80115" rotation="359.8901" />
    <Block type="SquareTiny" material="wood" x="2.42257" y="3.79979" rotation="-0.00282" />
    <Block type="SquareHole" material="ice" x="0.58041" y="3.26049" rotation="359.732" />
    <Block type="RectTiny" material="ice" x="0.28011" y="2.61355" rotation="89.71596" />
    <Block type="RectTiny" material="ice" x="0.89077" y="2.61105" rotation="89.7499" />
    <Block type="RectTiny" material="wood" x="0.27169" y="2.17174" rotation="89.8378" />
    <Block type="SquareTiny" material="stone" x="0.2726" y="1.83895" rotation="359.9589" />
    <Block type="RectTiny" material="wood" x="0.89411" y="2.17133" rotation="89.76949" />
    <Block type="SquareTiny" material="stone" x="0.89349" y="1.83928" rotation="359.7897" />
    <Block type="SquareHole" material="ice" x="1.49972" y="3.25817" rotation="359.9066" />
    <Block type="RectTiny" material="ice" x="1.20675" y="2.6105" rotation="89.75324" />
    <Block type="RectTiny" material="ice" x="1.81077" y="2.61046" rotation="89.90752" />
    <Block type="RectTiny" material="wood" x="1.19251" y="2.17127" rotation="89.77733" />
    <Block type="SquareTiny" material="stone" x="1.19229" y="1.83952" rotation="359.9229" />
    <Block type="RectTiny" material="wood" x="1.81291" y="2.17144" rotation="89.94759" />
    <Block type="SquareTiny" material="stone" x="1.8125" y="1.83971" rotation="359.9911" />
    <Block type="SquareHole" material="ice" x="2.4199" y="3.26155" rotation="0.01107" />
    <Block type="RectTiny" material="ice" x="2.12322" y="2.61279" rotation="89.92543" />
    <Block type="RectTiny" material="ice" x="2.73139" y="2.61329" rotation="89.98403" />
    <Block type="RectTiny" material="wood" x="2.1107" y="2.1719" rotation="90.00683" />
    <Block type="SquareTiny" material="stone" x="2.1117" y="1.83927" rotation="0.13769" />
    <Block type="RectTiny" material="wood" x="2.73271" y="2.172" rotation="89.97257" />
    <Block type="SquareTiny" material="stone" x="2.7322" y="1.8391" rotation="359.9879" />
    <Pig type="BasicSmall" x="1.43044" y="4.36132" rotation="0.30562" />
    <Platform type="Platform" x="0.475" y="1.555" rotation="0" scaleX="0.9922" scaleY="0.5156" />
    <Platform type="Platform" x="0.8825" y="1.555" rotation="0" scaleX="1" scaleY="0.5156" />
    <Platform type="Platform" x="1.5025" y="1.555" rotation="0" scaleX="1" scaleY="0.5156" />
    <Platform type="Platform" x="2.1225" y="1.555" rotation="0" scaleX="1" scaleY="0.5156" />
    <Platform type="Platform" x="2.5275" y="1.555" rotation="0" scaleX="0.9844" scaleY="0.5156" />
  </GameObjects>
</Level>
