<?xml version="1.0" encoding="utf-16"?>
<Level width="2">
	<Camera x="0" y="-1" minWidth="25" maxWidth="35" />
	<Score highScore="73352523" />
	<Birds>
		<Bird type="BirdBlue" />
		<Bird type="BirdRed" />
	</Birds>
	<Slingshot x="-12.0" y="-2.5" />
	<GameObjects>
		<Pig type="BasicSmall" material="" x="-4.2919" y="5.0354" rotation="0.5906" />
		<Pig type="BasicSmall" material="" x="-6.0907" y="-0.9181" rotation="0.2638" />
		<Block type="TriangleHole" material="ice" x="-6.0437" y="5.689" rotation="359.7452" />
		<Block type="RectFat" material="ice" x="-6.0433" y="5.0395" rotation="359.7249" />
		<Block type="RectMedium" material="wood" x="-6.3598" y="4.7018" rotation="359.7364" />
		<Block type="RectFat" material="ice" x="-7.0888" y="4.3664" rotation="359.6346" />
		<Block type="RectFat" material="ice" x="-5.5008" y="4.3595" rotation="359.9584" />
		<Block type="RectSmall" material="ice" x="-7.4045" y="3.7139" rotation="89.6055" />
		<Block type="RectSmall" material="wood" x="-7.0893" y="3.7118" rotation="89.5979" />
		<Block type="RectSmall" material="ice" x="-6.775" y="3.7097" rotation="89.6075" />
		<Block type="RectSmall" material="stone" x="-7.0897" y="3.1622" rotation="359.6029" />
		<Block type="RectFat" material="wood" x="-7.0902" y="2.8247" rotation="359.6201" />
		<Block type="RectTiny" material="wood" x="-7.404" y="2.4892" rotation="359.5612" />
		<Block type="RectTiny" material="wood" x="-6.7769" y="2.4849" rotation="359.759" />
		<Block type="RectTiny" material="wood" x="-7.4067" y="2.259" rotation="359.6837" />
		<Block type="RectTiny" material="wood" x="-7.4066" y="2.0292" rotation="359.8133" />
		<Block type="RectTiny" material="wood" x="-7.4064" y="1.7996" rotation="359.9399" />
		<Block type="SquareSmall" material="wood" x="-7.4046" y="1.4889" rotation="0.0046" />
		<Block type="RectTiny" material="wood" x="-6.7755" y="2.2545" rotation="359.8187" />
		<Block type="RectTiny" material="ice" x="-6.7782" y="2.0272" rotation="359.9181" />
		<Block type="RectTiny" material="wood" x="-6.7751" y="1.7998" rotation="0.0238" />
		<Block type="SquareSmall" material="wood" x="-6.7741" y="1.489" rotation="0.0235" />
		<Block type="RectSmall" material="wood" x="-5.8148" y="3.7054" rotation="89.9634" />
		<Block type="RectSmall" material="wood" x="-5.4991" y="3.7052" rotation="89.903" />
		<Block type="RectSmall" material="wood" x="-5.1845" y="3.7048" rotation="89.8772" />
		<Block type="RectSmall" material="wood" x="-5.5026" y="3.156" rotation="359.9067" />
		<Block type="RectFat" material="ice" x="-5.5024" y="2.8241" rotation="0.0011" />
		<Block type="RectTiny" material="ice" x="-5.814" y="2.4894" rotation="359.756" />
		<Block type="RectTiny" material="stone" x="-5.1862" y="2.4865" rotation="0.2884" />
		<Block type="RectTiny" material="wood" x="-5.8157" y="2.2621" rotation="359.8588" />
		<Block type="RectTiny" material="wood" x="-5.816" y="2.0327" rotation="359.939" />
		<Block type="RectTiny" material="stone" x="-5.815" y="1.8016" rotation="-0.0045" />
		<Block type="SquareSmall" material="wood" x="-5.8147" y="1.4901" rotation="0.0002" />
		<Block type="RectTiny" material="wood" x="-5.1847" y="2.2559" rotation="0.2566" />
		<Block type="RectTiny" material="wood" x="-5.1833" y="2.028" rotation="0.1875" />
		<Block type="RectTiny" material="wood" x="-5.1835" y="1.8005" rotation="0.1204" />
		<Block type="SquareSmall" material="stone" x="-5.1839" y="1.4901" rotation="0.0153" />
		<Block type="RectMedium" material="wood" x="-4.6397" y="4.7015" rotation="0.2435" />
		<Block type="RectFat" material="wood" x="-4.9612" y="5.0393" rotation="0.2378" />
		<Block type="CircleSmall" material="ice" x="-6.9192" y="5.037" rotation="358.699" />
		<Block type="TriangleHole" material="ice" x="-4.6725" y="5.6901" rotation="0.202" />
		<Block type="SquareSmall" material="wood" x="-4.2254" y="1.4888" rotation="359.9897" />
		<Block type="SquareSmall" material="stone" x="-3.595" y="1.4901" rotation="0.0045" />
		<Block type="RectTiny" material="wood" x="-4.2252" y="1.7985" rotation="359.8707" />
		<Block type="RectTiny" material="wood" x="-3.5949" y="1.8023" rotation="359.9892" />
		<Block type="RectTiny" material="stone" x="-4.2256" y="2.0292" rotation="359.8508" />
		<Block type="RectTiny" material="wood" x="-3.5949" y="2.034" rotation="0.0297" />
		<Block type="RectTiny" material="wood" x="-4.225" y="2.2606" rotation="359.834" />
		<Block type="RectTiny" material="ice" x="-3.5936" y="2.2643" rotation="0.0927" />
		<Block type="RectTiny" material="stone" x="-4.2255" y="2.4919" rotation="359.8067" />
		<Block type="RectTiny" material="ice" x="-3.5959" y="2.4931" rotation="0.178" />
		<Block type="RectFat" material="ice" x="-3.9091" y="2.8301" rotation="359.985" />
		<Block type="RectSmall" material="ice" x="-3.9029" y="3.1625" rotation="0.1503" />
		<Block type="RectSmall" material="wood" x="-4.2245" y="3.7098" rotation="90.2615" />
		<Block type="RectSmall" material="wood" x="-3.9097" y="3.7111" rotation="90.2213" />
		<Block type="RectFat" material="ice" x="-3.9103" y="4.3657" rotation="0.2531" />
		<Block type="RectSmall" material="wood" x="-3.595" y="3.7123" rotation="90.1716" />
		<Platform type="Platform" material="" x="-7.305" y="1.115" rotation="0.0" scaleX="0.9844" scaleY="0.5156" />
		<Platform type="Platform" material="" x="-6.74" y="1.115" rotation="0.0" scaleX="1.0" scaleY="0.5156" />
		<Platform type="Platform" material="" x="-5.5" y="1.115" rotation="0.0" scaleX="1.0" scaleY="0.5156" />
		<Platform type="Platform" material="" x="-6.12" y="1.115" rotation="0.0" scaleX="1.0" scaleY="0.5156" />
		<Platform type="Platform" material="" x="-4.88" y="1.115" rotation="0.0" scaleX="1.0" scaleY="0.5156" />
		<Platform type="Platform" material="" x="-4.26" y="1.115" rotation="0.0" scaleX="1.0" scaleY="0.5156" />
		<Platform type="Platform" material="" x="-3.695" y="1.115" rotation="0.0" scaleX="0.9844" scaleY="0.5156" />
		<Block type="Circle" material="ice" x="-5.8711" y="0.1484" rotation="0.3356" />
		<Block type="RectTiny" material="ice" x="-5.8667" y="-0.3502" rotation="0.0919" />
		<Block type="RectSmall" material="stone" x="-5.1301" y="-0.3488" rotation="359.9258" />
		<Block type="RectBig" material="stone" x="-5.5006" y="-0.5826" rotation="359.9583" />
		<Block type="RectTiny" material="ice" x="-6.445" y="-0.9188" rotation="90.0259" />
		<Block type="SquareSmall" material="stone" x="-5.4998" y="-0.9257" rotation="359.9749" />
		<Block type="RectFat" material="stone" x="-4.5808" y="-0.9223" rotation="0.0162" />
		<Block type="RectSmall" material="ice" x="-6.4299" y="-1.2528" rotation="0.5527" />
		<Block type="RectTiny" material="wood" x="-6.7316" y="-1.5943" rotation="90.1501" />
		<Block type="RectTiny" material="wood" x="-6.419" y="-1.5922" rotation="90.4207" />
		<Block type="RectTiny" material="stone" x="-6.1052" y="-1.5882" rotation="90.4987" />
		<Block type="SquareTiny" material="ice" x="-6.7366" y="-1.9269" rotation="0.1296" />
		<Block type="RectTiny" material="ice" x="-6.734" y="-2.2587" rotation="90.0887" />
		<Block type="SquareTiny" material="wood" x="-6.7337" y="-2.5913" rotation="0.0314" />
		<Block type="SquareTiny" material="ice" x="-6.4191" y="-1.9244" rotation="0.2707" />
		<Block type="RectTiny" material="wood" x="-6.4171" y="-2.2564" rotation="90.09" />
		<Block type="SquareTiny" material="stone" x="-6.4195" y="-2.5902" rotation="0.0143" />
		<Block type="SquareTiny" material="stone" x="-6.105" y="-1.9224" rotation="0.3794" />
		<Block type="RectTiny" material="stone" x="-6.1042" y="-2.2566" rotation="90.2406" />
		<Block type="SquareTiny" material="stone" x="-6.1035" y="-2.5907" rotation="0.1049" />
		<Block type="RectSmall" material="stone" x="-5.4998" y="-1.2461" rotation="359.9758" />
		<Block type="RectTiny" material="wood" x="-5.8143" y="-1.5858" rotation="89.9688" />
		<Block type="RectTiny" material="stone" x="-5.4999" y="-1.5861" rotation="89.9781" />
		<Block type="RectTiny" material="wood" x="-5.1859" y="-1.5861" rotation="89.9857" />
		<Block type="SquareTiny" material="stone" x="-5.8152" y="-1.9206" rotation="359.9769" />
		<Block type="RectTiny" material="wood" x="-5.8159" y="-2.2553" rotation="89.9877" />
		<Block type="SquareTiny" material="stone" x="-5.8149" y="-2.59" rotation="-0.0011" />
		<Block type="SquareTiny" material="wood" x="-5.5008" y="-1.9209" rotation="359.9857" />
		<Block type="RectTiny" material="wood" x="-5.5001" y="-2.2556" rotation="89.9941" />
		<Block type="SquareTiny" material="wood" x="-5.4989" y="-2.5903" rotation="0.0021" />
		<Block type="SquareTiny" material="wood" x="-5.1857" y="-1.9207" rotation="359.9913" />
		<Block type="RectTiny" material="wood" x="-5.1846" y="-2.2553" rotation="89.9972" />
		<Block type="SquareTiny" material="stone" x="-5.1848" y="-2.5901" rotation="-0.0018" />
		<Block type="RectSmall" material="wood" x="-4.5775" y="-1.2547" rotation="359.9774" />
		<Block type="RectTiny" material="wood" x="-4.8874" y="-1.5918" rotation="89.6646" />
		<Block type="RectTiny" material="wood" x="-4.5799" y="-1.5928" rotation="89.9981" />
		<Block type="RectTiny" material="stone" x="-4.2661" y="-1.5937" rotation="90.1188" />
		<Block type="SquareTiny" material="stone" x="-4.8965" y="-1.9245" rotation="359.7836" />
		<Block type="RectTiny" material="stone" x="-4.8958" y="-2.258" rotation="89.8834" />
		<Block type="SquareTiny" material="stone" x="-4.8946" y="-2.5913" rotation="359.9836" />
		<Block type="SquareTiny" material="stone" x="-4.5802" y="-1.9258" rotation="359.9917" />
		<Block type="RectTiny" material="stone" x="-4.58" y="-2.2593" rotation="90.0004" />
		<Block type="SquareTiny" material="wood" x="-4.5821" y="-2.5911" rotation="0.0655" />
		<Block type="SquareTiny" material="stone" x="-4.265" y="-1.9276" rotation="0.0763" />
		<Block type="RectTiny" material="stone" x="-4.2645" y="-2.2612" rotation="90.0271" />
		<Block type="SquareTiny" material="wood" x="-4.2677" y="-2.5932" rotation="0.0123" />
		<Block type="CircleSmall" material="ice" x="-4.8469" y="-0.0164" rotation="358.8315" />
		<Platform type="Platform" material="" x="-6.6325" y="-2.875" rotation="0.0" scaleX="0.6641" scaleY="0.5156" />
		<Platform type="Platform" material="" x="-6.12" y="-2.875" rotation="0.0" scaleX="1.0" scaleY="0.5156" />
		<Platform type="Platform" material="" x="-5.5" y="-2.875" rotation="0.0" scaleX="1.0" scaleY="0.5156" />
		<Platform type="Platform" material="" x="-4.88" y="-2.875" rotation="0.0" scaleX="1.0" scaleY="0.5156" />
		<Platform type="Platform" material="" x="-4.3675" y="-2.875" rotation="0.0" scaleX="0.6641" scaleY="0.5156" />
	</GameObjects>
</Level>
